transcribe_social.py
transcribe_social-1.0.6.dist-info/licenses/LICENSE
transcribe_social-1.0.6.dist-info/METADATA
transcribe_social-1.0.6.dist-info/WHEEL
transcribe_social-1.0.6.dist-info/entry_points.txt
transcribe_social-1.0.6.dist-info/top_level.txt
transcribe_social-1.0.6.dist-info/RECORD
