Metadata-Version: 2.4
Name: transcribe-social
Version: 1.0.6
Summary: Transcribe social media videos using OpenAI Whisper
Author-email: Rizwan <info@titandev.agency>
License-Expression: MIT
Project-URL: Source Code, https://github.com/mrizwan47/transcribe-social
Project-URL: Bug Tracker, https://github.com/mrizwan47/transcribe-social/issues
Keywords: transcription,whisper,video,audio,youtube,instagram,tiktok
Classifier: Development Status :: 4 - Beta
Classifier: Intended Audience :: Developers
Classifier: Intended Audience :: End Users/Desktop
Classifier: Topic :: Multimedia :: Video
Classifier: Topic :: Multimedia :: Sound/Audio :: Speech
Classifier: Programming Language :: Python :: 3
Classifier: Programming Language :: Python :: 3.11
Classifier: Programming Language :: Python :: 3.12
Classifier: Operating System :: OS Independent
Requires-Python: >=3.11
License-File: LICENSE
Requires-Dist: yt-dlp>=2023.1.6
Requires-Dist: openai-whisper>=20231117
Dynamic: license-file
